setup.py
folkmq/FolkMQ.py
folkmq/__init__.py
folkmq.egg-info/PKG-INFO
folkmq.egg-info/SOURCES.txt
folkmq.egg-info/dependency_links.txt
folkmq.egg-info/requires.txt
folkmq.egg-info/top_level.txt
folkmq.egg-info/zip-safe
folkmq/client/MqAlarm.py
folkmq/client/MqClient.py
folkmq/client/MqClientDefault.py
folkmq/client/MqClientListener.py
folkmq/client/MqMessage.py
folkmq/client/MqMessageReceived.py
folkmq/client/MqRouter.py
folkmq/client/MqSubscription.py
folkmq/client/MqTransaction.py
folkmq/client/__init__.py
folkmq/common/MqApis.py
folkmq/common/MqAssert.py
folkmq/common/MqConstants.py
folkmq/common/MqMetasResolver.py
folkmq/common/MqMetasResolverV1.py
folkmq/common/MqMetasResolverV2.py
folkmq/common/MqMetasResolverV3.py
folkmq/common/MqMetasV1.py
folkmq/common/MqMetasV2.py
folkmq/common/MqTopicHelper.py
folkmq/common/MqUtils.py
folkmq/common/__init__.py
folkmq/exception/FolkmqException.py
folkmq/exception/__init__.py