Metadata-Version: 2.1
Name: folkmq
Version: 1.7.13
Summary: @noear/folkmq python project
Home-page: https://folkmq.noear.org/
Author: noear
Classifier: Development Status :: 5 - Production/Stable
Classifier: Intended Audience :: Developers
Classifier: License :: OSI Approved
Classifier: Operating System :: OS Independent
Classifier: Programming Language :: Python
Classifier: Programming Language :: Python :: 3.10
Classifier: Topic :: Software Development :: Libraries
Requires-Python: >=3.10
Requires-Dist: loguru==0.7.2
Requires-Dist: websockets==12.0
Requires-Dist: socket.d==2.5.20
